assets/index.html.tpl
assets/script.js
assets/style.css.tpl
vidcardshare/__init__.py
vidcardshare/main.py
vidcardshare-0.1.3.dist-info/METADATA
vidcardshare-0.1.3.dist-info/WHEEL
vidcardshare-0.1.3.dist-info/entry_points.txt
vidcardshare-0.1.3.dist-info/RECORD
