Metadata-Version: 2.1
Name: vidcardshare
Version: 0.1.3
Summary: 
Home-page: https://github.com/arnos-stuff/vidcardshare.git
Author: Arno V
Author-email: bcda0276@gmail.com
Requires-Python: >=3.10,<4.0
Classifier: Programming Language :: Python :: 3
Classifier: Programming Language :: Python :: 3.10
Classifier: Programming Language :: Python :: 3.11
Requires-Dist: flask (>=2.3.2,<3.0.0)
Requires-Dist: jinja2 (>=3.1.2,<4.0.0)
Requires-Dist: pytube (>=15.0.0,<16.0.0)
Requires-Dist: typer-tinydb (>=0.1.4,<0.2.0)
